dlt_mcp/__init__.py
dlt_mcp/__main__.py
dlt_mcp/server.py
dlt_mcp/_prompts/__init__.py
dlt_mcp/_prompts/infer_table_reference.py
dlt_mcp/_tools/__init__.py
dlt_mcp/_tools/core.py
dlt_mcp/_tools/search.py
dlt_mcp/_utilities/__init__.py
dlt_mcp/_utilities/ingestion.py
dlt_mcp-0.2.0.dist-info/METADATA
dlt_mcp-0.2.0.dist-info/WHEEL
dlt_mcp-0.2.0.dist-info/licenses/LICENSE
dlt_mcp-0.2.0.dist-info/RECORD
