Metadata-Version: 2.4
Name: dlt-mcp
Version: 0.2.0
Summary: A Model Context Protocol (MCP) server for the Python library dlt.
Project-URL: Documentation, https://github.com/dlt-hub/dlt-mcp#README
Project-URL: Source, https://github.com/dlt-hub/dlt-mcp
Project-URL: Issues, https://github.com/dlt-hub/dlt-mcp/issues
Author: dltHub
Author-email: zilto <68975210+zilto@users.noreply.github.com>
License:                                 Apache License
License-File: LICENSE
Keywords: ai,data engineering,elt,etl,mcp
Classifier: Development Status :: 4 - Beta
Classifier: Intended Audience :: Developers
Classifier: License :: OSI Approved :: Apache Software License
Classifier: Operating System :: OS Independent
Classifier: Programming Language :: Python :: 3
Classifier: Topic :: Software Development :: Libraries
Classifier: Typing :: Typed
Requires-Python: >=3.10
Requires-Dist: dlt>=1.19.0
Requires-Dist: fastmcp>=2.11.3
Provides-Extra: duckdb
Requires-Dist: dlt[duckdb]>=1.19.0; extra == 'duckdb'
Provides-Extra: search
Requires-Dist: chonkie[code,model2vec]>=1.4.2; extra == 'search'
Requires-Dist: lancedb>=0.25.3; extra == 'search'
